[
  {
    "id": "68",
    "name": "अछाम",
    "name_en": "Achham"
  },
  {
    "id": "75",
    "name": "कञ्चनपुर",
    "name_en": "Kanchanpur"
  },
  {
    "id": "71",
    "name": "कैलाली",
    "name_en": "Kailali"
  },
  {
    "id": "74",
    "name": "डडेलधुरा",
    "name_en": "Dadeldhura"
  },
  {
    "id": "70",
    "name": "डोटी",
    "name_en": "Doti"
  },
  {
    "id": "72",
    "name": "दार्चुला",
    "name_en": "Darchula"
  },
  {
    "id": "69",
    "name": "बझाङ",
    "name_en": "Bajhang"
  },
  {
    "id": "67",
    "name": "बाजुरा",
    "name_en": "Bajura"
  },
  {
    "id": "73",
    "name": "बैतडी",
    "name_en": "Baitadi"
  }
]